Traffic-Light/TrafficLight.v
module TrafficLight(
    input wire Clock,
    input wire Reset,
    output reg Red,
    output reg Yellow,
    output reg Green
);

    parameter RedTime = 20;
    parameter RedYellowTime = 5;
    parameter GreenTime = 25;
    parameter YellowTime = 5;

    reg [1:0] State;    // 4 states: 00: RED, 01: RED-YELLOW, 10: GREEN, 11: YELLOW 

    integer Counter;    // Based on clock and to determine the time and state
    
    initial begin
        Red = 1'b0;
        Yellow = 1'b0;
        Green = 1'b0;
        State = 2'b00;
        Counter = 0;
    end

    always @(posedge Clock, negedge Clock, posedge Reset) begin    //posedge reset
        if (Reset) begin
            State = 2'b00;
            Red = 1'b0;
            Yellow = 1'b0;
            Green = 1'b0;
            Counter = 0;
        end 
        else begin
            case (State)
                2'b00: begin
                    Red = 1'b1;
                    Yellow = 1'b0;
                    Green = 1'b0;
                    Counter = Counter + 5;

                    if (Counter == RedTime) begin
                        State = 2'b01;
                    end
                end
                2'b01: begin
                    Red = 1'b1;
                    Yellow = 1'b1;
                    Green = 1'b0;
                    Counter = Counter + 5;

                    if (Counter == RedTime + RedYellowTime) begin
                        State = 2'b10;
                    end
                end
                2'b10: begin
                    Red = 1'b0;
                    Yellow = 1'b0;
                    Green = 1'b1;
                    Counter = Counter + 5;

                    if (Counter == RedTime + RedYellowTime + GreenTime) begin
                        State = 2'b11;
                    end
                end
                2'b11: begin
                    Red = 1'b0;
                    Yellow = 1'b1;
                    Green = 1'b0;
                    Counter = Counter + 5;

                    if (Counter == RedTime + RedYellowTime + GreenTime + YellowTime) begin
                        State = 2'b00;
                        Counter = 0;
                    end
                end
            endcase
        end
    end

endmodule

Traffic-Light/TrafficLight_tb.v
`include "TrafficLight.v"

module TrafficLight_tb;

    reg Clock;
    reg Reset;
    wire Red;
    wire Yellow;
    wire Green;

    TrafficLight TrafficLight0(
        .Clock(Clock),
        .Reset(Reset),
        .Red(Red),
        .Yellow(Yellow),
        .Green(Green)
    );

    initial begin
        $dumpfile("dump.vcd");
        $dumpvars(0, TrafficLight_tb);
        Clock = 0;
        Reset = 0;
        #10 Reset = 1;
        #10 Reset = 0;
        #105 Reset = 1;
        #10 Reset = 0;
        #200 $finish;
    end

    always #5 Clock = ~Clock;

endmodule

Traffic-Light/dump.vcd
$date
	Sun Feb 11 17:46:43 2024
$end
$version
	Icarus Verilog
$end
$timescale
	1s
$end
$scope module TrafficLight_tb $end
$var wire 1 ! Green $end
$var wire 1 " Red $end
$var wire 1 # Yellow $end
$var reg 1 $ Clock $end
$var reg 1 % Reset $end
$scope module TrafficLight0 $end
$var wire 1 & Clock $end
$var wire 1 ' Reset $end
$var integer 32 ( Counter [31:0] $end
$var reg 1 ) Green $end
$var reg 1 * Red $end
$var reg 2 + State [1:0] $end
$var reg 1 , Yellow $end
$upscope $end
$upscope $end
$enddefinitions $end
#0
$dumpvars
0,
b0 +
1*
0)
b101 (
0'
0&
0%
0$
0#
1"
0!
$end
#5
b1010 (
1$
1&
#10
b0 (
0*
0"
0$
0&
1%
1'
#15
1$
1&
#20
b101 (
1*
1"
0$
0&
0%
0'
#25
b1010 (
1$
1&
#30
b1111 (
0$
0&
#35
b1 +
b10100 (
1$
1&
#40
b10 +
b11001 (
1,
1#
0$
0&
#45
b11110 (
1)
1!
0,
0#
0*
0"
1$
1&
#50
b100011 (
0$
0&
#55
b101000 (
1$
1&
#60
b101101 (
0$
0&
#65
b11 +
b110010 (
1$
1&
#70
b0 +
b0 (
0)
0!
1,
1#
0$
0&
#75
b101 (
0,
0#
1*
1"
1$
1&
#80
b1010 (
0$
0&
#85
b1111 (
1$
1&
#90
b1 +
b10100 (
0$
0&
#95
b10 +
b11001 (
1,
1#
1$
1&
#100
b11110 (
1)
1!
0,
0#
0*
0"
0$
0&
#105
b100011 (
1$
1&
#110
b101000 (
0$
0&
#115
b101101 (
1$
1&
#120
b11 +
b110010 (
0$
0&
#125
b0 (
0)
0!
b0 +
1$
1&
1%
1'
#130
0$
0&
#135
b101 (
1*
1"
1$
1&
0%
0'
#140
b1010 (
0$
0&
#145
b1111 (
1$
1&
#150
b1 +
b10100 (
0$
0&
#155
b10 +
b11001 (
1,
1#
1$
1&
#160
b11110 (
1)
1!
0,
0#
0*
0"
0$
0&
#165
b100011 (
1$
1&
#170
b101000 (
0$
0&
#175
b101101 (
1$
1&
#180
b11 +
b110010 (
0$
0&
#185
b0 +
b0 (
0)
0!
1,
1#
1$
1&
#190
b101 (
0,
0#
1*
1"
0$
0&
#195
b1010 (
1$
1&
#200
b1111 (
0$
0&
#205
b1 +
b10100 (
1$
1&
#210
b10 +
b11001 (
1,
1#
0$
0&
#215
b11110 (
1)
1!
0,
0#
0*
0"
1$
1&
#220
b100011 (
0$
0&
#225
b101000 (
1$
1&
#230
b101101 (
0$
0&
#235
b11 +
b110010 (
1$
1&
#240
b0 +
b0 (
0)
0!
1,
1#
0$
0&
#245
b101 (
0,
0#
1*
1"
1$
1&
#250
b1010 (
0$
0&
#255
b1111 (
1$
1&
#260
b1 +
b10100 (
0$
0&
#265
b10 +
b11001 (
1,
1#
1$
1&
#270
b11110 (
1)
1!
0,
0#
0*
0"
0$
0&
#275
b100011 (
1$
1&
#280
b101000 (
0$
0&
#285
b101101 (
1$
1&
#290
b11 +
b110010 (
0$
0&
#295
b0 +
b0 (
0)
0!
1,
1#
1$
1&
#300
b101 (
0,
0#
1*
1"
0$
0&
#305
b1010 (
1$
1&
#310
b1111 (
0$
0&
#315
b1 +
b10100 (
1$
1&
#320
b10 +
b11001 (
1,
1#
0$
0&
#325
b11110 (
1)
1!
0,
0#
0*
0"
1$
1&
#330
b100011 (
0$
0&
#335
b101000 (
1$
1&
