MUX2x1/MUX2X1.v
module MUX2X1 (
    input wire D0,
    input wire D1,
    input wire S,
    output wire Y
);

    assign Y = ( D0 & ~S ) | ( D1 & S );

endmodule

MUX2x1/MUX2X1_tb.v
`include "MUX2X1.v"

module MUX2X1_tb;

    reg D0;
    reg D1;
    reg S;
    wire Y;

    MUX2X1 MUX2X1_inst (
        .D0(D0),
        .D1(D1),
        .S(S),
        .Y(Y)
    );

    initial begin
        $dumpfile("dump.vcd");
        $dumpvars(0, MUX2X1_tb);
        #10 D0 = 0; D1 = 0; S = 0;
        #10 D0 = 0; D1 = 0; S = 1;
        #10 D0 = 0; D1 = 1; S = 0;
        #10 D0 = 0; D1 = 1; S = 1;
        #10 D0 = 1; D1 = 0; S = 0;
        #10 D0 = 1; D1 = 0; S = 1;
        #10 D0 = 1; D1 = 1; S = 0;
        #10 D0 = 1; D1 = 1; S = 1;
        #10 $finish;
    end

endmodule

MUX2x1/dump.vcd
$date
	Sun Feb 11 17:22:40 2024
$end
$version
	Icarus Verilog
$end
$timescale
	1s
$end
$scope module MUX2X1_tb $end
$var wire 1 ! Y $end
$var reg 1 " D0 $end
$var reg 1 # D1 $end
$var reg 1 $ S $end
$scope module MUX2X1_inst $end
$var wire 1 % D0 $end
$var wire 1 & D1 $end
$var wire 1 ' S $end
$var wire 1 ! Y $end
$upscope $end
$upscope $end
$enddefinitions $end
#0
$dumpvars
x'
x&
x%
x$
x#
x"
x!
$end
#10
0!
0$
0'
0#
0&
0"
0%
#20
1$
1'
#30
0$
0'
1#
1&
#40
1!
1$
1'
#50
1!
0$
0'
0#
0&
1"
1%
#60
0!
1$
1'
#70
1!
0$
0'
1#
1&
#80
1$
1'
